astmain/__init__.py
astmain/class_base.py
astmain/colors.py
astmain/eval_func_str.py
astmain/log.py
astmain/log222_原始代码.py
astmain/log333_环境变量方式.py
astmain/cmd_exe/__init__.py
astmain/cmd_exe/run.py
astmain/desc/__init__.py
astmain/desc/log_try.py
astmain/desc/print_hook.py
astmain/fs/__init__.py
astmain/fs/calc.py
astmain/fs/calc222.py
astmain/fs/cwd.py
astmain/fs/delete.py
astmain/fs/fff.py
astmain/fs/fff222.py
astmain/fs/fff333.py
astmain/fs/fff444.py
astmain/fs/fs_find_file.py
astmain/fs/fs_write_add.py
astmain/fs/log_info.py
astmain/fs/read.py
astmain/fs/write.py
astmain/fs/write_add.py
astmain/is_data/__init__.py
astmain/is_data/is_arr.py
astmain/spider/__init__.py
astmain/spider/a2.py
astmain/spider/a3.py
astmain/spider/aaaa.py
astmain/spider/b1_位置恢复.py
astmain/spider/spider_pyppeteer.py
astmain/spider/spider_pyppeteer222_111.py
astmain/spider/spider_pyppeteer222_222.py
astmain/spider/spider_pyppeteer333_111.py
astmain/spider/wind_find_name.py
astmain/spider/任务栏问题11.py
astmain/spider/任务栏问题22.py
astmain/spider/任务栏问题33.py
astmain/spider/任务栏问题44.py
astmain/spider/任务栏问题55.py
astmain/spider/任务栏问题66.py
astmain/spider/任务栏问题77.py
astmain/spider/任务栏问题88.py
astmain/spider/程序设置_透明成功.py
astmain/spider/笔记_pyppeteer_设置_位置.py
astmain/to/__init__.py
astmain/to/num.py
astmain/to/str.py
astmain/to/to_json.py
astmain/to/to_obj_dict.py
astmain/to/type_vars.py
astmain/tool/__init__.py
astmain/tool/tool_await.py
astmain/win/__init__.py
astmain/win/win_find_name.py
astmain/win/win_find_name_all.py
astmain/win/win_hide_taskbar.py
astmain-0.0.155.dist-info/WHEEL
astmain-0.0.155.dist-info/METADATA
astmain-0.0.155.dist-info/RECORD
