Metadata-Version: 2.1
Name: astmain
Version: 0.0.155
Summary: 描述:我的工具包💗2024/07/01💗10_52_53#💗 pip install  astmain==0.0.155  
Author-email: xupeng <1311192345@qq.com>
Requires-Dist: tornado
Requires-Dist: pywin32
Requires-Dist: requests
Requires-Dist: pyppeteer
Requires-Dist: pyppeteer_stealth
Requires-Dist: arrow
